LICENSE
MANIFEST.in
README.md
setup.py
wagtail_blog/__init__.py
wagtail_blog/abstract.py
wagtail_blog/embed_finder.py
wagtail_blog/models.py
wagtail_blog/tests.py
wagtail_blog/urls.py
wagtail_blog/utils.py
wagtail_blog/views.py
wagtail_blog/wagtail_hooks.py
wagtail_blog/migrations/0001_initial.py
wagtail_blog/migrations/__init__.py
wagtail_blog/templates/base.html
wagtail_blog/templates/wagtail_blog/blog_index_page.html
wagtail_blog/templates/wagtail_blog/blog_page.html
wagtail_blog/templates/wagtail_blog/blog_post.html
wagtail_blog/templates/wagtail_blog/blog_post_comments_xtd.html
wagtail_blog/templates/wagtail_blog/blog_post_comments_xtd_link.html
wagtail_blog_simple.egg-info/PKG-INFO
wagtail_blog_simple.egg-info/SOURCES.txt
wagtail_blog_simple.egg-info/dependency_links.txt
wagtail_blog_simple.egg-info/requires.txt
wagtail_blog_simple.egg-info/top_level.txt