Metadata-Version: 2.1
Name: wagtail-blog-simple
Version: 1.0.6
Summary: Simple and customizable blog app for wagtail
Home-page: https://github.com/pupattan/wagtail-blog-simple
Author: Pulak Pattanayak
Author-email: pkbsdmp@gmail.com
License: MIT
Keywords: django wagtail wagtail_blog app
Platform: UNKNOWN
Classifier: Environment :: Web Environment
Classifier: Framework :: Django
Classifier: Intended Audience :: Developers
Classifier: Operating System :: OS Independent
Classifier: Topic :: Software Development
